[
  {
    "Type": "SeasonPassData",
    "Name": "FigmentPass_S03_Data",
    "Class": "UScriptClass'SeasonPassData'",
    "Flags": "RF_Public | RF_Standalone | RF_Transactional | RF_WasLoaded | RF_LoadCompleted",
    "Properties": {
      "Product": {
        "TagName": "Product.BR"
      },
      "SeasonName": {
        "Namespace": "",
        "Key": "6A58835846A9C24092F515AF9F99AEAF",
        "SourceString": "Chapter 1 - Season 3",
        "LocalizedString": "Сезон 3 главы 1"
      },
      "SeasonEndText": {
        "Namespace": "",
        "Key": "088E648F4962CE41BF454DB86BEBFDF9",
        "SourceString": "OG Pass end of season",
        "LocalizedString": "Пропуск «Как раньше»: конец сезона"
      },
      "SeasonStorefront": "FigmentS03",
      "SeasonPassOfferId": "0DFB3B8E44E6BE2C42E4F28320A129DF",
      "SeasonPassBundleOfferId": "0",
      "SeasonPassLevelOfferId": "EA9C3E2D4742085D179F5CBA55CEFBE7",
      "SeasonPassLevelBundleOfferId": "0",
      "LargeIcon": {
        "AssetPathName": "/SeasonPass/Materials/HeaderIcon/MI_UI_NexusHeaderIcon_OGPass.MI_UI_NexusHeaderIcon_OGPass",
        "SubPathString": ""
      },
      "SmallIcon": {
        "AssetPathName": "/SeasonPass/Materials/SideNavIcon/MI_UI_SideNavIcon_Figment.MI_UI_SideNavIcon_Figment",
        "SubPathString": ""
      },
      "BuyPassButtonName": {
        "Namespace": "",
        "Key": "DCA0E98A4E6B0674E837018F649E3248",
        "SourceString": "Get OG Pass",
        "LocalizedString": "Получить пропуск"
      },
      "ThemeData": {
        "SeasonColor": {
          "R": 0.341915,
          "G": 0.48515,
          "B": 0.982251,
          "A": 1.0,
          "Hex": "9EB9FD"
        },
        "ProgressionColor": {
          "R": 0.346704,
          "G": 0.783538,
          "B": 0.982251,
          "A": 1.0,
          "Hex": "9FE5FD"
        },
        "OverlayColor": {
          "R": 0.006049,
          "G": 0.002428,
          "B": 0.0,
          "A": 0.4,
          "Hex": "66120800"
        },
        "VaultBackgroundMaterial": {
          "AssetPathName": "/Figment_S03_PassData/UI/MaterialInstances/MI_UI_Figment_VaultWorld_Background_Surface.MI_UI_Figment_VaultWorld_Background_Surface",
          "SubPathString": ""
        },
        "UIBackgroundMaterial": {
          "AssetPathName": "/Figment_S03_PassData/UI/MaterialInstances/MI_UI_Figment_Background.MI_UI_Figment_Background",
          "SubPathString": ""
        },
        "UpsellBackgroundMaterial": {
          "AssetPathName": "/Figment_S03_PassData/UI/MaterialInstances/MI_UI_Figment_VaultWorld_Background_Upsell.MI_UI_Figment_VaultWorld_Background_Upsell",
          "SubPathString": ""
        },
        "CrewCategoryBackgroundMaterial": {
          "AssetPathName": "/Figment_S03_PassData/UI/MaterialInstances/MI_UI_Figment_CategoryButton_Crew_Background.MI_UI_Figment_CategoryButton_Crew_Background",
          "SubPathString": ""
        }
      }
    }
  }
]