{
  "": {
    "5480E1F941D7D93B362D71BA60CB7F14": "Выберите инструмент",
    "E70730D546323455388D0F8862938650": "Выберите инструмент",
    "94FB361A46082147B697C19A318D8F49": "Выберите песню",
    "27BE35C74D1FAAF01E9C2485C71B8C86": "Джем-партии",
    "48DAF18248B16009E2FD49BCC8CAF20D": "{Option}"
  },
  "JamTracksEmote": {
    "AllJamTracksCategory": "Джем-треки",
    "LockerJamTracksCategory": "Джем-треки из шкафчика"
  },
  "Sparks.SongItemDefinition": {
    "DefaultShortDescription": "Джем-трек"
  },
  "SparksCuratedSetlistStringsNS": {
    "daily_1_title": "Музыка на каждый день",
    "setlist_1_title": "Музыка на каждый день",
    "setlist_title_1": "Музыка на каждый день",
    "daily_1_desc": "Описание музыки на каждый день!",
    "setlist_1_desc": "Описание музыки на каждый день!",
    "setlist_desc_1": "Описание музыки на каждый день!",
    "festival_1_title": "Избранное фестиваля",
    "setlist_3_title": "Избранное фестиваля",
    "setlist_title_3": "Избранное фестиваля",
    "festival_1_desc": "Описание избранного фестиваля!",
    "setlist_3_desc": "Описание избранного фестиваля!",
    "setlist_desc_3": "Описание избранного фестиваля!",
    "setlist_desc_Fortnitemares": "Fortnite: кошмары",
    "setlist_title_Fortnitemares": "Fortnite: кошмары",
    "setlist_2_title": "Сетлист на сцене",
    "setlist_title_2": "Сет-лист «В центре внимания»",
    "spotlight_1_title": "Сетлист на сцене",
    "setlist_2_desc": "Описание сет-листа «В центре внимания»!",
    "setlist_desc_2": "Описание сет-листа «В центре внимания»!",
    "spotlight_1_desc": "Описание сет-листа «В центре внимания»!"
  },
  "SparksCuratedSetlistTitles": {
    "ProductMode_DisplayName_MainStage": "Пользовательский сет-лист",
    "ProductMode_DisplayName_Setlist1": "Ежедневный сет-лист",
    "Daily_1_Title": "Музыка на каждый день",
    "Daily_1_Desc": "Описание музыки на каждый день из таблицы",
    "Festival_1_Title": "Избранное фестиваля",
    "Festival_1_Desc": "Описание избранного фестиваля из таблицы",
    "Default_Title": "Сет-лист фестиваля",
    "ProductMode_DisplayName_Setlist3": "Сетлист на сцене",
    "Spotlight_1_Title": "Сетлист на сцене",
    "Spotlight_1_Desc": "Описание сет-листа «В центре внимания» из таблицы",
    "Default_Desc": "ЭТО ОПИСАНИЕ СЕТ-ЛИСТА ПО УМОЛЧАНИЮ!",
    "ProductMode_DisplayName_Setlist2": "Еженедельный сет-лист"
  },
  "SparksFilters": {
    "SparksArtistSort": "Имя исполнителя",
    "SparksAvailableFilter": "Доступные",
    "SparksDefaultFilter": "По умолчанию",
    "SparksFeaturedSort": "Рекомендуемое",
    "SparksFeaturedFilter": "Новое и рекомендованное",
    "SparksOwnedFilter": "Ваши",
    "SparksOwnedSort": "Владелец",
    "SparksSongSecondaryFilterUnarchivedOnly": "Отображать архив",
    "SparksAlphaSort": "Название песни (по алфавиту)",
    "SparksAlphaSortReverse": "Название песни (в обр. порядке)"
  },
  "SparksSongItemDetails": {
    "ItemCategoryName": "{Year} | {Duration}"
  }
}